f2r-2.11.0.data/scripts/f2r
flp2rpm/Defaults.py
flp2rpm/Fpm.py
flp2rpm/Module.py
flp2rpm/Package.py
flp2rpm/Repo.py
flp2rpm/S3.py
flp2rpm/__init__.py
flp2rpm/after_install_template.sh
flp2rpm/after_remove_template.sh
flp2rpm/config.py
flp2rpm/devel.slc7.yaml
flp2rpm/devel.slc8.yaml
flp2rpm/devel.slc9.yaml
flp2rpm/helpers.py
flp2rpm/runtime.slc7.yaml
flp2rpm/runtime.slc8.yaml
flp2rpm/runtime.slc9.yaml
f2r-2.11.0.dist-info/COPYING
f2r-2.11.0.dist-info/METADATA
f2r-2.11.0.dist-info/WHEEL
f2r-2.11.0.dist-info/top_level.txt
f2r-2.11.0.dist-info/RECORD
