Metadata-Version: 2.1
Name: f2r
Version: 2.11.0
Summary: Produces RPMs for FLP packages out of aliBuild ouput
Home-page: https://gitlab.cern.ch/AliceO2Group/flp-to-rpm
Author: Barthelemy von Haller
Author-email: bvonhall@cern.ch
License: GPLv3
Classifier: License :: OSI Approved :: GNU General Public License v3 (GPLv3)
Classifier: Programming Language :: Python :: 3
Classifier: Topic :: Utilities
Classifier: Environment :: Console
Classifier: Operating System :: Unix
Classifier: Development Status :: 4 - Beta
Requires-Python: >=3.9
License-File: COPYING
Requires-Dist: PyYAML
Requires-Dist: coloredlogs
Requires-Dist: s3cmd
Requires-Dist: alibuild
